rtl/alu.sv
import riscv_pkg::*;

module alu (
	input  logic [31:0] a,
	input  logic [31:0] b,
	input  alu_op_t alu_op,
	output logic [31:0] result,
	output logic zero
);

	logic [4:0] shamt;
	assign shamt = b[4:0];

	always_comb begin
		case(alu_op)
			ALU_ADD: 
				result = a + b;
			ALU_SUB:
				result = a - b;
			ALU_AND:
				result = a & b;
			ALU_OR:
				result = a | b;
			ALU_XOR:
				result = a ^ b;
			ALU_SLL:
				result = a << shamt;
			ALU_SRL:
				result = a >> shamt;
			ALU_SRA:
				result = $signed(a) >>> shamt;
			ALU_SLT:
				result = ($signed(a) < $signed(b)) ? 32'd1 : 32'd0;
			ALU_SLTU:
				result = (a < b) ? 32'd1 : 32'd0;
			default: result = 32'b0;
		endcase
	end

	assign zero = (result == 32'b0);

endmodule

tb/alu_tb.sv
`timescale 1ns/1ps

import riscv_pkg::*;

module alu_tb;
	logic [31:0] a_tb;
	logic [31:0] b_tb;
	alu_op_t alu_op_tb;
	logic [31:0] result_tb;
	logic zero_tb;

	alu dut (
		.a(a_tb),
		.b(b_tb),
		.alu_op(alu_op_tb),
		.result(result_tb),
		.zero(zero_tb)
	);

	initial begin
		$dumpfile("sim/alu_wave.vcd");
		$dumpvars(0, alu_tb);

		$monitor("Time=%0t | Op=%b | A=%d | B=%d | Res=%d | Zero=%b", $time, alu_op_tb, a_tb, b_tb, result_tb, zero_tb);

		a_tb = 32'd10;
		b_tb = 32'd20;
		alu_op_tb = ALU_ADD;
		#10;

		alu_op_tb = ALU_SUB;
		#10;

		alu_op_tb = ALU_AND;
		#10;

		alu_op_tb = ALU_OR;
		#10;

		alu_op_tb = ALU_XOR;
		#10;

		alu_op_tb = ALU_SLL;
		#10;

		alu_op_tb = ALU_SRL;
		#10;

		alu_op_tb = ALU_SRA;
		#10;

		alu_op_tb = ALU_SLT;
		#10;

		alu_op_tb = ALU_SLTU;
		#10;

		$finish;
	end

endmodule

sim/alu_wave.vcd
$date
	Thu Feb  5 00:00:50 2026
$end
$version
	Icarus Verilog
$end
$timescale
	1ps
$end
$scope module alu_tb $end
$var wire 1 ! zero_tb $end
$var wire 32 " result_tb [31:0] $end
$var reg 32 # a_tb [31:0] $end
$var reg 4 $ alu_op_tb [3:0] $end
$var reg 32 % b_tb [31:0] $end
$scope module dut $end
$var wire 32 & a [31:0] $end
$var wire 4 ' alu_op [3:0] $end
$var wire 32 ( b [31:0] $end
$var wire 1 ! zero $end
$var wire 5 ) shamt [4:0] $end
$var reg 32 * result [31:0] $end
$upscope $end
$upscope $end
$enddefinitions $end
$comment Show the parameter values. $end
$dumpall
$end
#0
$dumpvars
b11110 *
b10100 )
b10100 (
b0 '
b1010 &
b10100 %
b0 $
b1010 #
b11110 "
0!
$end
#10000
b11111111111111111111111111110110 "
b11111111111111111111111111110110 *
b1 $
b1 '
#20000
1!
b0 "
b0 *
b10 $
b10 '
#30000
0!
b11110 "
b11110 *
b11 $
b11 '
#40000
b100 $
b100 '
#50000
b101000000000000000000000 "
b101000000000000000000000 *
b101 $
b101 '
#60000
1!
b0 "
b0 *
b110 $
b110 '
#70000
b111 $
b111 '
#80000
0!
b1 "
b1 *
b1000 $
b1000 '
#90000
b1001 $
b1001 '
