rtl/alu.sv
module alu (
    input logic [31:0] a,
    input logic [31:0] b,
    input logic [2:0] alu_control,
    output logic [31:0] result,
    output logic zero
);

    always_comb begin
        case (alu_control)
            3'b000: result = a + b;
            3'b001: result = a - b;
            3'b010: result = a & b;
            3'b011: result = a | b;
            3'b101: result = (a < b) ? 32'd1 : 32'd0;
            default: result = 32'b0;
        endcase
    end

    // Co Zero: Neu ket qua bang 0 thi bat len 1
    assign zero = (result == 32'b0);

endmodule

tb/alu_tb.sv
`timescale 1ns/1ps

module alu_tb;
    logic [31:0] a_tb;
    logic [31:0] b_tb;
    logic [2:0] alu_control_tb; // 3 bit dieu khien
    
    logic [31:0] result_tb;
    logic zero_tb;

    alu dut (
        .a(a_tb),
        .b(b_tb),
        .alu_control(alu_control_tb),
        .result(result_tb),
        .zero(zero_tb)
    );

    // Kich ban kiem thu
    initial begin
        $dumpfile("sim/alu_wave.vcd");
        $dumpvars(0, alu_tb);

        $monitor("Time=%0t | A=%d | B=%d | Control=%b | Res=%d | Zero=%b", $time, a_tb, b_tb, alu_control_tb, result_tb, zero_tb);

        // 10 + 20 = 30
        a_tb = 32'd10; b_tb = 32'd20; alu_control_tb = 3'b000;
        #10;

        // 20 - 10 = 10
        a_tb = 32'd20; b_tb = 32'd10; alu_control_tb = 3'b001;
        #10;

        // 10 - 20 = -10
        a_tb = 32'd10; b_tb = 32'd20; alu_control_tb = 3'b001;
        #10;

        // 00001111 AND 01010101 = 00000101
        a_tb = 32'h0F; b_tb = 32'h55; alu_control_tb = 3'b010;
        #10;

        // 00001111 OR 01010101 = 01011111
        a_tb = 32'h0F; b_tb = 32'h55; alu_control_tb = 3'b011;
        #10;

        // So sanh be hon giua 10 va 20
        a_tb = 32'd10; b_tb = 32'd20; alu_control_tb = 3'b101;
        #10;
        a_tb = 32'd20; b_tb = 32'd10; alu_control_tb = 3'b101;
        #10;

        // Kiem tra co Zero
        a_tb = 32'd50; b_tb = 32'd50; alu_control_tb = 3'b001;
        #10;

        $finish;
    end

endmodule

sim/alu_wave.vcd
$date
	Fri Feb 13 23:35:16 2026
$end
$version
	Icarus Verilog
$end
$timescale
	1ps
$end
$scope module alu_tb $end
$var wire 1 ! zero_tb $end
$var wire 32 " result_tb [31:0] $end
$var reg 32 # a_tb [31:0] $end
$var reg 3 $ alu_control_tb [2:0] $end
$var reg 32 % b_tb [31:0] $end
$scope module dut $end
$var wire 32 & a [31:0] $end
$var wire 3 ' alu_control [2:0] $end
$var wire 32 ( b [31:0] $end
$var wire 1 ! zero $end
$var reg 32 ) result [31:0] $end
$upscope $end
$upscope $end
$enddefinitions $end
$comment Show the parameter values. $end
$dumpall
$end
#0
$dumpvars
b11110 )
b10100 (
b0 '
b1010 &
b10100 %
b0 $
b1010 #
b11110 "
0!
$end
#10000
b1010 "
b1010 )
b1 $
b1 '
b1010 %
b1010 (
b10100 #
b10100 &
#20000
b11111111111111111111111111110110 "
b11111111111111111111111111110110 )
b10100 %
b10100 (
b1010 #
b1010 &
#30000
b101 "
b101 )
b10 $
b10 '
b1010101 %
b1010101 (
b1111 #
b1111 &
#40000
b1011111 "
b1011111 )
b11 $
b11 '
#50000
b1 "
b1 )
b101 $
b101 '
b10100 %
b10100 (
b1010 #
b1010 &
#60000
1!
b0 "
b0 )
b1010 %
b1010 (
b10100 #
b10100 &
#70000
b1 $
b1 '
b110010 %
b110010 (
b110010 #
b110010 &
