rtl/regfile.sv
module regfile (
	input logic clk,
	input logic rst_n,

	// Cong doc
	input logic [4:0] rs1_addr,
	input logic [4:0] rs2_addr,
	output logic [31:0] rdata1,
	output logic [31:0] rdata2,

	// Cong ghi
	input logic we,
	input logic [4:0] rd_addr,
	input logic [31:0] wdata
);

	logic [31:0] rf [31:0];
	integer i;

	// Ghi
	always_ff @(posedge clk or negedge rst_n) begin
		if (!rst_n) begin
			for (i = 0; i < 32; i++) begin
				rf[i] <= 32'b0;
			end
		end else begin
			if (we && (rd_addr != 5'b0)) begin
				rf[rd_addr] <= wdata;
			end
		end
	end

	// Doc
	assign rdata1 = (rs1_addr == 5'b0) ? 32'b0 : rf[rs1_addr];
	assign rdata2 = (rs2_addr == 5'b0) ? 32'b0 : rf[rs2_addr];

endmodule

tb/regfile_tb.sv
`timescale 1ns/1ps

module regfile_tb;
    logic clk;
    logic rst_n_tb;
    logic [4:0] rs1_addr_tb, rs2_addr_tb, rd_addr_tb;
    logic we_tb;
    logic [31:0] wdata_tb;
    logic [31:0] rdata1_tb, rdata2_tb;

    regfile dut (
        .clk(clk),
        .rst_n(rst_n_tb),
        .rs1_addr(rs1_addr_tb),
        .rs2_addr(rs2_addr_tb),
        .rdata1(rdata1_tb),
        .rdata2(rdata2_tb),
        .we(we_tb),
        .rd_addr(rd_addr_tb),
        .wdata(wdata_tb)
    );

    initial begin
        clk = 0;
        forever #5 clk = ~clk;
    end

    initial begin
        $dumpfile("sim/regfile_wave.vcd");
        $dumpvars(0, regfile_tb);
        
        $monitor("Time=%0t | We=%b | Write_addr=%d | Data=%h | Read1_addr=%d | Out1=%h | Read2_addr=%d | Out2=%h", $time, we_tb, rd_addr_tb, wdata_tb, rs1_addr_tb, rdata1_tb, rs2_addr_tb, rdata2_tb);

        rst_n_tb = 0; we_tb = 0; rs1_addr_tb = 0; rs2_addr_tb = 0; 
		rd_addr_tb = 0; wdata_tb = 0;
        #10;
        rst_n_tb = 1;
        #10;

        // Ghi gia tri 0xADCBECAF vao thanh ghi so 1
        @(posedge clk);
        we_tb = 1; rd_addr_tb = 5'd1; wdata_tb = 32'hADCBECAF;
        #10;
        
        @(posedge clk);
        we_tb = 0;
        rs1_addr_tb = 5'd1;
        #5;

        // Thu ghi du lieu vao thanh ghi x0
        @(posedge clk);
        we_tb = 1; rd_addr_tb = 5'd0; wdata_tb = 32'hFFFFFFFF;
        
        @(posedge clk);
        we_tb = 0;
        rs1_addr_tb = 5'd0;
        #5;

        // Doc 2 cong cung mot luc
        // Ghi vao thanh ghi so 2 gia tri 0xFDACBDAC
        @(posedge clk);
        we_tb = 1; rd_addr_tb = 5'd2; wdata_tb = 32'hFDACBDAC;
        @(posedge clk);
        we_tb = 0;
        rs1_addr_tb = 5'd1;
        rs2_addr_tb = 5'd2;
        #10;

        $finish;
    end

endmodule

sim/regfile_wave.vcd
$date
	Fri Feb 13 00:04:44 2026
$end
$version
	Icarus Verilog
$end
$timescale
	1ps
$end
$scope module regfile_tb $end
$var wire 32 ! rdata2_tb [31:0] $end
$var wire 32 " rdata1_tb [31:0] $end
$var reg 1 # clk $end
$var reg 5 $ rd_addr_tb [4:0] $end
$var reg 5 % rs1_addr_tb [4:0] $end
$var reg 5 & rs2_addr_tb [4:0] $end
$var reg 1 ' rst_n_tb $end
$var reg 32 ( wdata_tb [31:0] $end
$var reg 1 ) we_tb $end
$scope module dut $end
$var wire 1 # clk $end
$var wire 5 * rd_addr [4:0] $end
$var wire 5 + rs1_addr [4:0] $end
$var wire 5 , rs2_addr [4:0] $end
$var wire 1 ' rst_n $end
$var wire 32 - wdata [31:0] $end
$var wire 1 ) we $end
$var wire 32 . rdata2 [31:0] $end
$var wire 32 / rdata1 [31:0] $end
$var integer 32 0 i [31:0] $end
$upscope $end
$upscope $end
$enddefinitions $end
$comment Show the parameter values. $end
$dumpall
$end
#0
$dumpvars
b100000 0
b0 /
b0 .
b0 -
b0 ,
b0 +
b0 *
0)
b0 (
0'
b0 &
b0 %
b0 $
0#
b0 "
b0 !
$end
#5000
b100000 0
1#
#10000
0#
1'
#15000
1#
#20000
0#
#25000
b10101101110010111110110010101111 (
b10101101110010111110110010101111 -
b1 $
b1 *
1)
1#
#30000
0#
#35000
b10101101110010111110110010101111 "
b10101101110010111110110010101111 /
b1 %
b1 +
0)
1#
#40000
0#
#45000
b11111111111111111111111111111111 (
b11111111111111111111111111111111 -
b0 $
b0 *
1)
1#
#50000
0#
#55000
b0 "
b0 /
b0 %
b0 +
0)
1#
#60000
0#
#65000
b11111101101011001011110110101100 (
b11111101101011001011110110101100 -
b10 $
b10 *
1)
1#
#70000
0#
#75000
b11111101101011001011110110101100 !
b11111101101011001011110110101100 .
b10101101110010111110110010101111 "
b10101101110010111110110010101111 /
b10 &
b10 ,
b1 %
b1 +
0)
1#
