rtl/dmem.sv
module dmem (
	input logic clk,
	input logic we,
	input logic [31:0] addr,
	input logic [31:0] wdata,
	output logic [31:0] rdata
);
	// Tao mang RAM
	logic [31:0] RAM [0:63];
	
	// Doc du lieu
	assign rdata = RAM[addr[31:2]];

	// Ghi du lieu
	always_ff @(posedge clk) begin
		if (we) begin
			RAM[addr[31:2]] <= wdata;
		end
	end

endmodule

rtl/imem.sv
module imem (
	input logic [31:0] addr,
	output logic [31:0] data
);
	
	// Tao mang bo nho RAM
	logic [31:0] RAM [0:63];
	
	// Doc file program.hex va nap vao RAM
	initial begin
		$readmemh("program.hex", RAM);
	end

	// Doc du lieu tu RAM
	assign data = RAM[addr[31:2]];

endmodule

rtl/control_unit.sv
module control_unit (
    input logic [6:0] op, // Opcode (7 bit cuoi cua lenh)
    input logic [2:0] funct3, // Funct3 (Bit [14-12])
    input logic funct7b5, // Funct7 bit 5 (Bit 30 phan biet ADD/SUB)
    input logic zero, // Tin hieu Zero tu ALU de bao hieu a == b
    
    output logic pc_src, // 0: PC+4, 1: PC+Imm
    output logic [1:0] result_src, // 00: ALU, 01: Mem, 10: PC+4
    output logic mem_write, // 1: Ghi bo nho (Store)
    output logic alu_src, // 0: RegB, 1: Imm
    output logic reg_write, // 1: Ghi thanh ghi (RegFile)
    output logic [2:0] alu_control // Lenh dieu khien ALU
);

    logic [1:0] alu_op; // Tin hieu trung gian
    logic branch; // Lenh re nhanh
    logic jump; // Lenh nhay

    // Bo giai ma chinh
    always_comb begin
        // Gia tri mac dinh
        branch = 0;
        jump = 0;
        result_src = 2'b00;
        mem_write = 0;
        alu_src = 0;
        reg_write = 0;
        alu_op = 2'b00;

        case (op)
            // Lenh R-Type (ADD, SUB, AND, OR)
            7'b0110011: begin
                reg_write = 1;
                alu_op = 2'b10; // Bat ALU Decoder
            end

            // Lenh I-Type (ADDI, ANDI)
            7'b0010011: begin
                reg_write = 1;
                alu_src = 1; // Lay so Imm
                alu_op = 2'b10; // Bat ALU Decoder
            end

            // Lệnh LW
            7'b0000011: begin
                reg_write = 1;
                alu_src = 1;
                result_src = 2'b01; // Lay tu Mem
                alu_op = 2'b00; // ALU Cong (tinh dia chi)
            end

            // Lệnh SW
            7'b0100011: begin
                mem_write = 1;
                alu_src = 1;
                alu_op = 2'b00; // ALU Cong
            end

            // Lệnh BEQ
            7'b1100011: begin
                branch = 1;
                alu_op = 2'b01; // ALU Tru (so sanh)
            end
            
            // Lệnh JAL
            7'b1101111: begin
                jump = 1;
                result_src = 2'b10; // Luu PC+4
                reg_write = 1;
                alu_src = 1; 
            end
        endcase
    end

    // Giai ma chi tiet cho ALU
    always_comb begin
        case (alu_op)
            2'b00: alu_control = 3'b000; // Cong (cho LW, SW)
            2'b01: alu_control = 3'b001; // Tru (cho BEQ)
            default: begin // R-Type hoac I-Type
                case (funct3)
                    3'b000: begin
                        if (op == 7'b0110011 && funct7b5) 
                            alu_control = 3'b001; // SUB
                        else 
							alu_control = 3'b000; // ADD
                    end
                    3'b010: alu_control = 3'b101; // SLT
                    3'b110: alu_control = 3'b011; // OR
                    3'b111: alu_control = 3'b010; // AND
                    default: alu_control = 3'b000;
                endcase
            end
        endcase
    end

    // Logic Pc_src
    assign pc_src = jump | (branch & zero);

endmodule

rtl/alu.sv
module alu (
    input logic [31:0] a,
    input logic [31:0] b,
    input logic [2:0] alu_control,
    output logic [31:0] result,
    output logic zero
);

    always_comb begin
        case (alu_control)
            3'b000: result = a + b;
            3'b001: result = a - b;
            3'b010: result = a & b;
            3'b011: result = a | b;
            3'b101: result = (a < b) ? 32'd1 : 32'd0;
            default: result = 32'b0;
        endcase
    end

    // Co Zero: Neu ket qua bang 0 thi bat len 1
    assign zero = (result == 32'b0);

endmodule

rtl/immgen.sv
module immgen (
    input  logic [31:0] inst, // Instruction lay tu IMEM
    output logic [31:0] imm
);

    always @(*) begin
        case (inst[6:0])
            // Lenh I-Type
            // Opcode: 0010011 (ADDI), 0000011 (LW), 1100111 (JALR)
            7'b0010011, 7'b0000011, 7'b1100111: begin
                imm = {{20{inst[31]}}, inst[31:20]};
            end

            // Lenh S-Type
            // Opcode: 0100011 (SW)
            7'b0100011: begin
                imm = {{20{inst[31]}}, inst[31:25], inst[11:7]};
            end

            // Lenh B-Type
            // Opcode: 1100011 (Branch)
            7'b1100011: begin
                imm = {{20{inst[31]}}, inst[7], inst[30:25], inst[11:8], 1'b0};
            end

            // Lenh U-Type
            // Opcode: 0110111 (LUI), 0010111 (AUIPC)
            7'b0110111, 7'b0010111: begin
                imm = {inst[31:12], 12'b0};
            end

            // Lenh J-Type
            // Opcode: 1101111 (JAL)
            7'b1101111: begin
                imm = {{12{inst[31]}}, inst[19:12], inst[20], inst[30:21], 1'b0};
            end

            default: imm = 32'b0;
        endcase
    end

endmodule

rtl/regfile.sv
module regfile (
    input logic clk,
    input logic rst_n,
    input logic we3, // Write enable
    input logic [4:0] a1, // Read address 1
    input logic [4:0] a2, // Read address 2
    input logic [4:0] a3, // Write address
    input logic [31:0] wd3, // Write data
    output logic [31:0] rd1, // Read data 1
    output logic [31:0] rd2 // Read data 2
);

    logic [31:0] rf [0:31];

    // Doc du lieu
    assign rd1 = (a1 != 0) ? rf[a1] : 32'b0;
    assign rd2 = (a2 != 0) ? rf[a2] : 32'b0;

    // Ghi du lieu
    always_ff @(posedge clk) begin
        if (!rst_n) begin
        end else if (we3) begin
             rf[a3] <= wd3;
        end
    end

endmodule

rtl/pc.sv
module pc (
    input logic clk,
    input logic rst_n,
    input logic [31:0] pc_next,
    output logic [31:0] pc_out
);

    always_ff @(posedge clk or negedge rst_n) begin
        if (!rst_n) begin
            pc_out <= 32'b0;
        end else begin
            pc_out <= pc_next;
        end
    end

endmodule

rtl/datapath.sv
module datapath (
    input logic clk,
    input logic rst_n,
    
    // Cac tin hieu dieu khien tu Control Unit
    input logic reg_write, // Co viet vao RegFile
    input logic alu_src, // Chon dau vao B cho ALU (0: Reg, 1: Imm)
    input logic pc_src, // Chon PC tiep theo (0: PC+4, 1: PC_Target)
    input logic [1:0] result_src, // Chon ket qua ghi vao Reg (ALU, Mem, PC+4)
    input logic [2:0] alu_control, // Lenh cho ALU
    input logic [31:0] instr, // Lenh hien tai lay tu IMEM
    input logic [31:0] read_data, // Du lieu doc tu bo nho lay tu DMEM

    // Cac tin hieu gui ra cho Control Unit va Memory
    output logic zero, // Co Zero cua ALU
    output logic [31:0] pc_out, // Dia chi PC hien tai gui cho IMEM
    output logic [31:0] alu_result, // Ket qua ALU dung lam dia chi cho DMEM
    output logic [31:0] write_data   // Du lieu can ghi de gui cho DMEM
);

    logic [31:0] pc_next, pc_plus4, pc_target;
    logic [31:0] imm_ext;
    logic [31:0] src_a, src_b;
    logic [31:0] result;

    // Khoi PC
    pc my_pc (
        .clk(clk),
        .rst_n(rst_n),
        .pc_next(pc_next),
        .pc_out(pc_out)
    );

    // Logic tinh PC tiep theo
    assign pc_plus4 = pc_out + 4;
    assign pc_target = pc_out + imm_ext; // PC khi nhay (Branch/JAL)

    // Bo MUX chon PC
    assign pc_next = (pc_src) ? pc_target : pc_plus4;

    // Khoi Regfile
    regfile my_rf (
        .clk(clk),
        .rst_n(rst_n),
        .we3(reg_write),
        .a1(instr[19:15]), // rs1
        .a2(instr[24:20]), // rs2
        .a3(instr[11:7]), // rd (Thanh ghi dich)
        .wd3(result), // Du lieu can ghi
        .rd1(src_a), // Dau ra A (Noi vao ALU)
        .rd2(write_data) // Dau ra B (Noi vao ALU hoac DMEM)
    );

    // Khoi Immgen
    immgen my_immgen (
        .inst(instr),
        .imm(imm_ext)
    );

    // Khoi ALU
    // Neu alu_src=0: Lay tu RegFile (write_data)
    // Neu alu_src=1: Lay tu ImmGen (imm_ext)
    assign src_b = (alu_src) ? imm_ext : write_data;

    alu my_alu (
        .a(src_a),
        .b(src_b),
        .alu_control(alu_control),
        .result(alu_result),
        .zero(zero)
    );

    // Bo MUX de chon ket qua cuoi cung
    // Ket qua quay ve ghi vao RegFile
    // 00: ALU (Lenh tinh toan)
    // 01: ReadData (Lenh Load tu bo nho)
    // 10: PC+4 (Lenh JAL/JALR de luu dia chi tra ve)
    always_comb begin
        case (result_src)
            2'b00: result = alu_result;
            2'b01: result = read_data;
            2'b10: result = pc_plus4;
            default: result = 32'b0;
        endcase
    end

endmodule

rtl/riscv_top.sv
module riscv_top (
    input logic clk,
    input logic rst_n,
    output logic [31:0] test_result
);
    
    // Khai bao day noi noi bo
    logic [31:0] instr;
    logic [31:0] pc, alu_result, write_data, read_data;
    logic zero;
    
    // Cac tin hieu dieu khien
    logic pc_src;
    logic [1:0] result_src;
    logic mem_write;
    logic alu_src;
    logic reg_write;
    logic [2:0] alu_control;
    logic funct7b5;

    // Datapath
    datapath dp (
        .clk(clk),
        .rst_n(rst_n),
        .reg_write(reg_write),
        .alu_src(alu_src),
        .pc_src(pc_src),
        .result_src(result_src),
        .alu_control(alu_control),
        .instr(instr),
        .read_data(read_data),
        .zero(zero),
        .pc_out(pc),
        .alu_result(alu_result),
        .write_data(write_data)
    );

    // Control Unit
    assign funct7b5 = instr[30];

    control_unit cu (
        .op(instr[6:0]),
        .funct3(instr[14:12]),
        .funct7b5(funct7b5),
        .zero(zero),
        .pc_src(pc_src),
        .result_src(result_src),
        .mem_write(mem_write),
        .alu_src(alu_src),
        .reg_write(reg_write),
        .alu_control(alu_control)
    );

    // Bo nho lenh (IMEM)
    imem my_imem (
        .addr(pc),
        .data(instr)
    );

    // Bo nho du lieu (DMEM)
    dmem my_dmem (
        .clk(clk),
        .we(mem_write),
        .addr(alu_result),
        .wdata(write_data),
        .rdata(read_data)
    );

    // Dua ket qua ALU ra ngoai de xem tren song
    assign test_result = alu_result;

endmodule

tb/riscv_tb.sv
`timescale 1ns/1ps

module riscv_tb;
    // Khai bao tin hieu
    logic clk;
    logic rst_n;
    logic [31:0] test_result; // Gia tri ALU Result dua ra ngoai

    // Goi con CPU
    riscv_top dut (
        .clk(clk),
        .rst_n(rst_n),
        .test_result(test_result)
    );

    // Tao xung Clock
    initial begin
        clk = 0;
        forever #5 clk = ~clk;
    end

    // Kich ban chay thu
    initial begin
        $dumpfile("sim/riscv_wave.vcd");
        $dumpvars(0, riscv_tb);
        
        $monitor("Time=%0t | PC=%d | Result(ALU)=%d", $time, dut.pc, test_result);

        rst_n = 0;
        #10;
        rst_n = 1;
        
        // Cho CPU chay khoang 100ns (du cho 5 cau lenh)
        #100;
        
        $finish;
    end

endmodule

sim/riscv_wave.vcd
$date
	Sat Feb 14 00:17:20 2026
$end
$version
	Icarus Verilog
$end
$timescale
	1ps
$end
$scope module riscv_tb $end
$var wire 32 ! test_result [31:0] $end
$var reg 1 " clk $end
$var reg 1 # rst_n $end
$scope module dut $end
$var wire 1 " clk $end
$var wire 1 # rst_n $end
$var wire 32 $ test_result [31:0] $end
$var wire 1 % zero $end
$var wire 32 & write_data [31:0] $end
$var wire 2 ' result_src [1:0] $end
$var wire 1 ( reg_write $end
$var wire 32 ) read_data [31:0] $end
$var wire 1 * pc_src $end
$var wire 32 + pc [31:0] $end
$var wire 1 , mem_write $end
$var wire 32 - instr [31:0] $end
$var wire 1 . funct7b5 $end
$var wire 1 / alu_src $end
$var wire 32 0 alu_result [31:0] $end
$var wire 3 1 alu_control [2:0] $end
$scope module cu $end
$var wire 3 2 funct3 [2:0] $end
$var wire 1 . funct7b5 $end
$var wire 7 3 op [6:0] $end
$var wire 1 * pc_src $end
$var wire 1 % zero $end
$var reg 3 4 alu_control [2:0] $end
$var reg 2 5 alu_op [1:0] $end
$var reg 1 / alu_src $end
$var reg 1 6 branch $end
$var reg 1 7 jump $end
$var reg 1 , mem_write $end
$var reg 1 ( reg_write $end
$var reg 2 8 result_src [1:0] $end
$upscope $end
$scope module dp $end
$var wire 3 9 alu_control [2:0] $end
$var wire 1 / alu_src $end
$var wire 1 " clk $end
$var wire 1 * pc_src $end
$var wire 1 ( reg_write $end
$var wire 2 : result_src [1:0] $end
$var wire 1 # rst_n $end
$var wire 1 % zero $end
$var wire 32 ; write_data [31:0] $end
$var wire 32 < src_b [31:0] $end
$var wire 32 = src_a [31:0] $end
$var wire 32 > read_data [31:0] $end
$var wire 32 ? pc_target [31:0] $end
$var wire 32 @ pc_plus4 [31:0] $end
$var wire 32 A pc_out [31:0] $end
$var wire 32 B pc_next [31:0] $end
$var wire 32 C instr [31:0] $end
$var wire 32 D imm_ext [31:0] $end
$var wire 32 E alu_result [31:0] $end
$var reg 32 F result [31:0] $end
$scope module my_alu $end
$var wire 3 G alu_control [2:0] $end
$var wire 32 H b [31:0] $end
$var wire 1 % zero $end
$var wire 32 I a [31:0] $end
$var reg 32 J result [31:0] $end
$upscope $end
$scope module my_immgen $end
$var wire 32 K inst [31:0] $end
$var reg 32 L imm [31:0] $end
$upscope $end
$scope module my_pc $end
$var wire 1 " clk $end
$var wire 32 M pc_next [31:0] $end
$var wire 1 # rst_n $end
$var reg 32 N pc_out [31:0] $end
$upscope $end
$scope module my_rf $end
$var wire 5 O a1 [4:0] $end
$var wire 5 P a2 [4:0] $end
$var wire 5 Q a3 [4:0] $end
$var wire 1 " clk $end
$var wire 1 # rst_n $end
$var wire 32 R wd3 [31:0] $end
$var wire 1 ( we3 $end
$var wire 32 S rd2 [31:0] $end
$var wire 32 T rd1 [31:0] $end
$upscope $end
$upscope $end
$scope module my_dmem $end
$var wire 32 U addr [31:0] $end
$var wire 1 " clk $end
$var wire 32 V rdata [31:0] $end
$var wire 32 W wdata [31:0] $end
$var wire 1 , we $end
$upscope $end
$scope module my_imem $end
$var wire 32 X addr [31:0] $end
$var wire 32 Y data [31:0] $end
$upscope $end
$upscope $end
$upscope $end
$enddefinitions $end
$comment Show the parameter values. $end
$dumpall
$end
#0
$dumpvars
b101000000000000010010011 Y
b0 X
bx W
bx V
b1010 U
b0 T
bx S
b1010 R
b1 Q
b1010 P
b0 O
b0 N
b100 M
b1010 L
b101000000000000010010011 K
b1010 J
b0 I
b1010 H
b0 G
b1010 F
b1010 E
b1010 D
b101000000000000010010011 C
b100 B
b0 A
b100 @
b1010 ?
bx >
b0 =
b1010 <
bx ;
b0 :
b0 9
b0 8
07
06
b10 5
b0 4
b10011 3
b0 2
b0 1
b1010 0
1/
0.
b101000000000000010010011 -
0,
b0 +
0*
bx )
1(
b0 '
bx &
0%
b1010 $
0#
0"
b1010 !
$end
#5000
1"
#10000
0"
1#
#15000
b10100 F
b10100 R
b10100 !
b10100 $
b10100 0
b10100 E
b10100 J
b10100 U
b10100 <
b10100 H
b10 Q
b10100 P
b10100 D
b10100 L
b1010000000000000100010011 -
b1010000000000000100010011 C
b1010000000000000100010011 K
b1010000000000000100010011 Y
b1000 B
b1000 M
b11000 ?
b1000 @
b100 +
b100 A
b100 N
b100 X
1"
#20000
0"
#25000
b11110 F
b11110 R
b11110 !
b11110 $
b11110 0
b11110 E
b11110 J
b11110 U
b10100 &
b10100 ;
b10100 S
b10100 W
b1010 =
b1010 I
b1010 T
b10 5
1(
0/
b10100 <
b10100 H
b11 Q
b10 P
b1 O
b110011 3
b0 D
b0 L
b1000001000000110110011 -
b1000001000000110110011 C
b1000001000000110110011 K
b1000001000000110110011 Y
b1100 B
b1100 M
b1000 ?
b1100 @
b1000 +
b1000 A
b1000 N
b1000 X
1"
#30000
0"
#35000
b100 F
b100 R
b100 !
b100 $
b100 0
b100 E
b100 J
b100 U
b100 <
b100 H
b11110 &
b11110 ;
b11110 S
b11110 W
b0 =
b0 I
b0 T
1/
1,
b0 5
0(
b100 Q
b11 P
b0 O
b10 2
b100011 3
b100 D
b100 L
b1100000010001000100011 -
b1100000010001000100011 C
b1100000010001000100011 K
b1100000010001000100011 Y
b10000 B
b10000 M
b10000 ?
b10000 @
b1100 +
b1100 A
b1100 N
b1100 X
1"
#40000
0"
#45000
b11110 F
b11110 R
bx &
bx ;
bx S
bx W
b1 '
b1 8
b1 :
1(
1/
0,
b100 P
b11 3
b10000000010001000000011 -
b10000000010001000000011 C
b10000000010001000000011 K
b10000000010001000000011 Y
b10100 B
b10100 M
b10100 ?
b10100 @
b10000 +
b10000 A
b10000 N
b10000 X
b11110 )
b11110 >
b11110 V
1"
#50000
0"
#55000
bx )
bx >
bx V
bx F
bx R
x%
bx !
bx $
bx 0
bx E
bx J
bx U
bx =
bx I
bx T
0(
0/
b0 '
b0 8
b0 :
bx <
bx H
bx Q
bx P
bx O
bx 2
bx 3
x.
b0 D
b0 L
bx -
bx C
bx K
bx Y
b11000 B
b11000 M
bx &
bx ;
bx S
bx W
b10100 ?
b11000 @
b10100 +
b10100 A
b10100 N
b10100 X
1"
#60000
0"
#65000
b11100 B
b11100 M
b11000 ?
b11100 @
b11000 +
b11000 A
b11000 N
b11000 X
1"
#70000
0"
#75000
b100000 B
b100000 M
b11100 ?
b100000 @
b11100 +
b11100 A
b11100 N
b11100 X
1"
#80000
0"
#85000
b100100 B
b100100 M
b100000 ?
b100100 @
b100000 +
b100000 A
b100000 N
b100000 X
1"
#90000
0"
#95000
b101000 B
b101000 M
b100100 ?
b101000 @
b100100 +
b100100 A
b100100 N
b100100 X
1"
#100000
0"
#105000
b101100 B
b101100 M
b101000 ?
b101100 @
b101000 +
b101000 A
b101000 N
b101000 X
1"
